bandplot/__init__.py
bandplot/mass.py
bandplot/plots.py
bandplot/pplots.py
bandplot/projected.py
bandplot/readdata.py
bandplot/wrapper.py
bandplot-0.1.6.1.dist-info/METADATA
bandplot-0.1.6.1.dist-info/WHEEL
bandplot-0.1.6.1.dist-info/entry_points.txt
bandplot-0.1.6.1.dist-info/top_level.txt
bandplot-0.1.6.1.dist-info/RECORD
