Metadata-Version: 2.1
Name: bandplot
Version: 0.1.6.1
Summary: Band structure, DOS or phonon band structure plot from vaspkit or phonopy result.
Home-page: https://github.com/lkccrr/bandplot
Author: kan
Author-email: luo_kan+pypi@outlook.com
License: MIT
Keywords: DFT VASP DOS band plot Phonon
Platform: Unix
Platform: Windows
Classifier: License :: OSI Approved :: MIT License
Classifier: Programming Language :: Python
Classifier: Programming Language :: Python :: 3
Classifier: Programming Language :: Python :: 3 :: Only
Classifier: Programming Language :: Python :: 3.6
Classifier: Programming Language :: Python :: 3.7
Classifier: Programming Language :: Python :: 3.8
Classifier: Programming Language :: Python :: 3.9
Classifier: Programming Language :: Python :: 3.10
Classifier: Programming Language :: Python :: 3.11
Classifier: Programming Language :: Python :: 3.12
Requires-Python: >=3.6
Requires-Dist: numpy (>=1.22.0)
Requires-Dist: matplotlib (>=3.4.0)
